github2pandas/__init__.py
github2pandas/core.py
github2pandas/git_releases.py
github2pandas/github2pandas.py
github2pandas/issues.py
github2pandas/pull_requests.py
github2pandas/repository.py
github2pandas/version.py
github2pandas/workflows.py
github2pandas-2.0.2.dist-info/LICENSE
github2pandas-2.0.2.dist-info/METADATA
github2pandas-2.0.2.dist-info/WHEEL
github2pandas-2.0.2.dist-info/top_level.txt
github2pandas-2.0.2.dist-info/RECORD
