Metadata-Version: 2.1
Name: github2pandas
Version: 2.0.2
Summary: github2pandas supports the aggregation of project activities in a GitHub repository and makes them available in pandas dataframes
Home-page: https://github.com/TUBAF-IFI-DiPiT/github2pandas
Download-URL: https://github.com/TUBAF-IFI-DiPiT/github2pandas/archive/github2pandas-2.0.2.tar.gz
Author: Maximilian Karl & Sebastian Zug
License: BSD 2
Keywords: git,github,collaborative code development,git mining
Classifier: Programming Language :: Python :: 3
Classifier: Operating System :: OS Independent
Requires-Python: >=3.9
License-File: LICENSE
Requires-Dist: pygit2 (>=1.9.1)
Requires-Dist: requests (>=2.27.1)
Requires-Dist: pygithub (>=1.55)
Requires-Dist: git2net (>=1.6.0)
Requires-Dist: pysqlite3 (>=0.4.7)
Requires-Dist: pandas (>=1.2.4)
Requires-Dist: human-id (>=0.2.0)
Requires-Dist: xlsxwriter (>=3.0.3)
